pepecoin/__init__.py
pepecoin/account.py
pepecoin/cli.py
pepecoin/pepecoin.py
pepecoin/pepecoin_rpc.py
pepecoin/test_pepecoin.py
pepecoin/test_transfer.py
pepecoin/utils.py
pepecoin/scripts/build_openssl1_1_from_source.sh
pepecoin/scripts/pepecoind.service
pepecoin/scripts/run_setup_test.sh
pepecoin/scripts/run_transfer_test.sh
pepecoin/scripts/setup_pepecoin_node.sh
pepecoin/scripts/setup_pepecoin_node_macos.sh
pepecoin/scripts/virgin_vm.sh
pepecoin-0.0.16.dist-info/METADATA
pepecoin-0.0.16.dist-info/WHEEL
pepecoin-0.0.16.dist-info/entry_points.txt
pepecoin-0.0.16.dist-info/top_level.txt
pepecoin-0.0.16.dist-info/RECORD
