Metadata-Version: 2.1
Name: pepecoin
Version: 0.0.16
Summary: PEPECOIN class to interact with pepecoin blockchain in a easy way
Author: we are all PEPE
Classifier: Development Status :: 3 - Alpha
Classifier: Intended Audience :: Developers
Classifier: License :: OSI Approved :: MIT License
Classifier: Programming Language :: Python :: 3
Classifier: Programming Language :: Python :: 3.7
Classifier: Programming Language :: Python :: 3.8
Classifier: Programming Language :: Python :: 3.9
Classifier: Programming Language :: Python :: 3.10
Classifier: Operating System :: OS Independent
Requires-Python: >=3.7
Requires-Dist: pydantic
Requires-Dist: requests
Requires-Dist: indented_logger
Requires-Dist: pyyaml
Requires-Dist: python-bitcoinrpc
Requires-Dist: python-dotenv
Requires-Dist: python-bitcoinrpc
Requires-Dist: click
